jinjaturtle/__init__.py
jinjaturtle/cli.py
jinjaturtle/core.py
jinjaturtle/handlers/__init__.py
jinjaturtle/handlers/base.py
jinjaturtle/handlers/dict.py
jinjaturtle/handlers/ini.py
jinjaturtle/handlers/json.py
jinjaturtle/handlers/postfix.py
jinjaturtle/handlers/systemd.py
jinjaturtle/handlers/toml.py
jinjaturtle/handlers/xml.py
jinjaturtle/handlers/yaml.py
jinjaturtle/loop_analyzer.py
jinjaturtle/multi.py
jinjaturtle-0.4.0.dist-info/LICENSE
jinjaturtle-0.4.0.dist-info/METADATA
jinjaturtle-0.4.0.dist-info/WHEEL
jinjaturtle-0.4.0.dist-info/entry_points.txt
jinjaturtle-0.4.0.dist-info/RECORD
