Metadata-Version: 2.1
Name: jinjaturtle
Version: 0.4.0
Summary: Convert config files into Ansible defaults and Jinja2 templates.
Home-page: https://git.mig5.net/mig5/jinjaturtle
License: GPL-3.0-or-later
Keywords: ansible,jinja2,config,toml,ini,yaml,json,devops
Author: Miguel Jacq
Author-email: mig@mig5.net
Requires-Python: >=3.10,<4.0
Classifier: License :: OSI Approved :: GNU General Public License v3 or later (GPLv3+)
Classifier: Programming Language :: Python :: 3
Classifier: Programming Language :: Python :: 3.10
Classifier: Programming Language :: Python :: 3.11
Classifier: Programming Language :: Python :: 3.12
Requires-Dist: PyYAML (>=6.0,<7.0)
Requires-Dist: defusedxml (>=0.7.1,<0.8.0)
Requires-Dist: jinja2 (>=3.1.6,<4.0.0)
Requires-Dist: tomli (>=2.0.0,<3.0.0) ; python_version < "3.11"
Project-URL: Repository, https://git.mig5.net/mig5/jinjaturtle
